py_cyclo/__init__.py
py_cyclo/main.py
py_cyclo/controllers/__init__.py
py_cyclo/controllers/complexity_controller.py
py_cyclo/models/__init__.py
py_cyclo/models/complexity_model.py
py_cyclo/services/__init__.py
py_cyclo/services/complexity_service.py
py_cyclo/views/__init__.py
py_cyclo/views/complexity_view.py
py_cyclo-1.2.0.dist-info/entry_points.txt
py_cyclo-1.2.0.dist-info/licenses/LICENSE
py_cyclo-1.2.0.dist-info/WHEEL
py_cyclo-1.2.0.dist-info/METADATA
py_cyclo-1.2.0.dist-info/RECORD
