Metadata-Version: 2.4
Name: py-cyclo
Version: 1.2.0
Summary: A general purpose tool for validating cyclomatic complexity in Python.
Author-email: Omar Crosby <omar.crosby@gmail.com>
License-File: LICENSE
Requires-Dist: click
Requires-Dist: radon
Requires-Dist: tabulate
Requires-Dist: toml
Requires-Dist: build ; extra == "dev"
Requires-Dist: pytest ; extra == "dev"
Requires-Dist: pytest-cov ; extra == "dev"
Requires-Dist: pytest-mock ; extra == "dev"
Requires-Dist: mypy ; extra == "dev"
Requires-Dist: black ; extra == "dev"
Requires-Dist: flake8 ; extra == "dev"
Requires-Dist: isort ; extra == "dev"
Requires-Dist: pylint ; extra == "dev"
Provides-Extra: dev
